<?xml version="1.0" ?>
<world>
	<graspableBody>
		<filename>/home/liujian/WorkSpace/EBM_Hand/grasp_generation/vr_shapes/43.xml</filename>
		<transform>
			<fullTransform>(+1 +0 +0 +0)[+0 +0 +0]</fullTransform>
		</transform>
	</graspableBody>
	<robot>
		<filename>/home/liujian/WorkSpace/EBM_Hand/grasp_generation/graspitmodified_lm/graspit/models/robots/HumanHand/HumanHand20DOF.xml</filename>
		<dofValues>+0.349066 +0.243752 +0.00484207 +0.00484207 +1.76049e-16 +0.318164 -0.134533 -0.0282829 -0.164653 +0.476468 -0.0682829 +0.454842 -0.523599 +0.518183 -0.0770329 +0.754842 +0.318943 -0.841288 +1.5708 +1.74533 </dofValues>
		<transform>
			<fullTransform>(+0.641206 -0.621713 +0.376887 -0.245528)[+101.156 -148.005 -92.629]</fullTransform>
		</transform>
	</robot>
	<camera>
		<position>+24.526 -40.7866 +370.241</position>
		<orientation>+0 +0 +0 +1</orientation>
		<focalDistance>+294.666</focalDistance>
	</camera>
</world>
