<?xml version="1.0" ?>
<world>
	<graspableBody>
		<filename>/home/liujian/WorkSpace/EBM_Hand/grasp_generation/vr_shapes/43.xml</filename>
		<transform>
			<fullTransform>(+1 +0 +0 +0)[+0 +0 +0]</fullTransform>
		</transform>
	</graspableBody>
	<robot>
		<filename>/home/liujian/WorkSpace/EBM_Hand/grasp_generation/graspitmodified_lm/graspit/models/robots/HumanHand/HumanHand20DOF.xml</filename>
		<dofValues>+0.349066 +0.870681 +1.53484 +1.31769 +2.95844e-16 +0.174913 +0.394191 +0.00796356 -0.322835 +0.596984 -0.0320329 +0.0454373 -0.523599 +0.926755 -0.164533 +0.517967 +1.22173 -0.872665 +1.5708 +1.74533 </dofValues>
		<transform>
			<fullTransform>(+0.481927 -0.440595 -0.572149 +0.496254)[-30.7758 +184.474 -47.0556]</fullTransform>
		</transform>
	</robot>
	<camera>
		<position>-30.1543 +56.5828 +282.878</position>
		<orientation>+0 +0 +0 +1</orientation>
		<focalDistance>+208.139</focalDistance>
	</camera>
</world>
